touch_timestamp/app.py
touch_timestamp/controller.py
touch_timestamp/touch_timestamp.py
touch_timestamp/utils.py
touch_timestamp-0.5.1.dist-info/LICENSE
touch_timestamp-0.5.1.dist-info/METADATA
touch_timestamp-0.5.1.dist-info/WHEEL
touch_timestamp-0.5.1.dist-info/entry_points.txt
touch_timestamp-0.5.1.dist-info/RECORD
