Metadata-Version: 2.3
Name: touch-timestamp
Version: 0.5.1
Summary: Change file timestamps with a dialog window.
License: GPL-3.0-or-later
Author: Edvard Rejthar
Author-email: edvard.rejthar@nic.cz
Requires-Python: >=3.10,<4.0
Classifier: License :: OSI Approved :: GNU General Public License v3 or later (GPLv3+)
Classifier: Programming Language :: Python :: 3
Classifier: Programming Language :: Python :: 3.10
Classifier: Programming Language :: Python :: 3.11
Classifier: Programming Language :: Python :: 3.12
Classifier: Programming Language :: Python :: 3.13
Provides-Extra: heif
Requires-Dist: mininterface[basic] (>=1.1,<2.0)
Requires-Dist: pydash
Requires-Dist: python-dateutil
Project-URL: Homepage, https://github.com/CZ-NIC/touch-timestamp
